README.md
setup.py
ok_anime/__init__.py
ok_anime/ok_anime.py
ok_anime.egg-info/PKG-INFO
ok_anime.egg-info/SOURCES.txt
ok_anime.egg-info/dependency_links.txt
ok_anime.egg-info/requires.txt
ok_anime.egg-info/top_level.txt