Metadata-Version: 2.1
Name: ok-anime
Version: 1.0
Summary: python wrapper for OKanime
Home-page: https://github.com/user/reponame
Author: Etherl
Author-email: None@domain.com
License: MIT
Download-URL: https://github.com/Etherll/OKanime
Keywords: ok,ok anime,anime
Platform: UNKNOWN
Classifier: Development Status :: 3 - Alpha
Classifier: Intended Audience :: Developers
Classifier: Topic :: Software Development :: Build Tools
Classifier: License :: OSI Approved :: MIT License
Classifier: Programming Language :: Python :: 3
Classifier: Programming Language :: Python :: 3.4
Classifier: Programming Language :: Python :: 3.5
Classifier: Programming Language :: Python :: 3.6
